afkarena/__init__.py
afkarena/cookiejar.py
afkarena/errors.py
afkarena/http.py
afkarena/player.py
afkarena/user.py
afkarena-0.2.0.dist-info/WHEEL
afkarena-0.2.0.dist-info/METADATA
afkarena-0.2.0.dist-info/RECORD
