Metadata-Version: 2.1
Name: afkarena
Version: 0.2.0
Summary: Simple API wrapper for the AFK Arena site https://cdkey.lilith.com/afk-global.
Home-page: https://github.com/scragly/afkarena
License: MIT
Keywords: afk,arena,afkarena,gift,giftcode
Author: scragly
Author-email: 29337040+scragly@users.noreply.github.com
Requires-Python: >=3.9,<4.0
Classifier: Development Status :: 4 - Beta
Classifier: Intended Audience :: Developers
Classifier: License :: OSI Approved :: MIT License
Classifier: Programming Language :: Python :: 3
Classifier: Programming Language :: Python :: 3.9
Classifier: Topic :: Software Development :: Libraries
Classifier: Topic :: Utilities
Requires-Dist: aiohttp (>=3.7.4,<4.0.0)
Project-URL: Repository, https://github.com/scragly/afkarena
